{
  "groupings": {
  },
  "dependencies": {
    "nagios": ">= 0.0.0"
  },
  "providing": {
  },
  "maintainer": "NationalField, LLC",
  "conflicting": {
  },
  "recommendations": {
  },
  "maintainer_email": "engineers@nationalfield.com",
  "license": "MIT",
  "recipes": {
  },
  "attributes": {
  },
  "version": "0.1.0",
  "name": "nagios-ext",
  "platforms": {
  },
  "long_description": "Description\n===========\n\nRequirements\n============\n\nAttributes\n==========\n\nUsage\n=====\n\n",
  "replacing": {
  },
  "suggestions": {
  },
  "description": "Installs/Configures nagios-ext"
}